linkedin_post_craft/__init__.py
linkedin_post_craft/main.py
linkedin_post_craft/prompts.py
linkedin_post_craft-2025.12.21172241.dist-info/METADATA
linkedin_post_craft-2025.12.21172241.dist-info/WHEEL
linkedin_post_craft-2025.12.21172241.dist-info/top_level.txt
linkedin_post_craft-2025.12.21172241.dist-info/RECORD
