Metadata-Version: 2.4
Name: linkedin-post-craft
Version: 2025.12.21172241
Summary: A new package that generates professional LinkedIn posts from user-provided text input. Users can input their key points, achievements, or ideas, and the package will return a well-structured LinkedIn
Author-email: linkedin-post-craft <hi@eugene.plus>
License: MIT
Project-URL: Homepage, https://github.com/chigwell/linkedin-post-craft
Requires-Python: >=3.9
Requires-Dist: langchain-llm7>=0.0.0
Requires-Dist: llmatch-messages>=0.0.0
Requires-Dist: langchain-core>=0.3.0
